MANIFEST.in
setup.cfg
setup.py
nfq/__init__.py
nfq.egg-info/PKG-INFO
nfq.egg-info/SOURCES.txt
nfq.egg-info/dependency_links.txt
nfq.egg-info/not-zip-safe
nfq.egg-info/top_level.txt