Metadata-Version: 1.0
Name: nfq
Version: 0.1.1
Summary: NFQ Solutions base package
Home-page: UNKNOWN
Author: NFQ Solutions
Author-email: solutions@nfq.es
License: UNKNOWN
Platform: UNKNOWN
